bin/IsoSpecCppPy.dll
IsoSpecPy/__init__.py
IsoSpecPy/__main__.py
IsoSpecPy/Advanced.py
IsoSpecPy/approximations.py
IsoSpecPy/confs_passthrough.py
IsoSpecPy/Distributions.py
IsoSpecPy/Formulas.py
IsoSpecPy/isoFFI.py
IsoSpecPy/IsoSpec++/allocator.h
IsoSpecPy/IsoSpec++/btrd.h
IsoSpecPy/IsoSpec++/conf.h
IsoSpecPy/IsoSpec++/cwrapper.h
IsoSpecPy/IsoSpec++/dirtyAllocator.h
IsoSpecPy/IsoSpec++/element_tables.h
IsoSpecPy/IsoSpec++/fasta.h
IsoSpecPy/IsoSpec++/fixedEnvelopes.h
IsoSpecPy/IsoSpec++/isoMath.h
IsoSpecPy/IsoSpec++/isoSpec++.h
IsoSpecPy/IsoSpec++/marginalTrek++.h
IsoSpecPy/IsoSpec++/misc.h
IsoSpecPy/IsoSpec++/mman.h
IsoSpecPy/IsoSpec++/operators.h
IsoSpecPy/IsoSpec++/platform.h
IsoSpecPy/IsoSpec++/platform_incl.h
IsoSpecPy/IsoSpec++/pod_vector.h
IsoSpecPy/IsoSpec++/summator.h
IsoSpecPy/IsoSpecPy.py
IsoSpecPy/IsoSpecPyOld.py
IsoSpecPy/PeriodicTbl.py
lib/IsoSpecCppPy.lib
isospecpy-2.3.2.dist-info/METADATA
isospecpy-2.3.2.dist-info/WHEEL
isospecpy-2.3.2.dist-info/licenses/LICENCE
isospecpy-2.3.2.dist-info/RECORD
