Metadata-Version: 2.4
Name: IsoSpecPy
Version: 2.3.2
Summary: IsoSpecPy is a Python library for computing isotopic distributions of molecules.
Keywords: isotopic distribution,mass spectrometry,chemistry,isotopic envelope,isotopologues
Author: Michał Startek, Mateusz Łącki
License-Expression: BSD-2-Clause
License-File: LICENCE
Classifier: Programming Language :: Python :: 3
Classifier: Programming Language :: Python :: 3.6
Classifier: Topic :: Software Development :: Libraries :: Python Modules
Classifier: Development Status :: 5 - Production/Stable
Classifier: Operating System :: OS Independent
Project-URL: Homepage, https://github.com/MatteoLacki/IsoSpec
Project-URL: Repository, https://github.com/MatteoLacki/IsoSpec
Requires-Python: >=3.6
Requires-Dist: cffi
Provides-Extra: testing
Requires-Dist: pytest; extra == "testing"
Requires-Dist: OldIsoSpecPy; extra == "testing"
